docbot_app/__init__.py
docbot_app/src/DocBot.py
docbot_app/src/__init__.py
docbot_app/src/api.py
docbot_app/src/arg_parser.py
docbot_app/src/file_handler.py
docbot_app/tests/__init__.py
docbot_app/tests/test_api.py
docbot_app/tests/test_argparser.py
docbot_app/tests/test_docbot.py
docbot_ai-1.0.1.dist-info/LICENSE
docbot_ai-1.0.1.dist-info/METADATA
docbot_ai-1.0.1.dist-info/WHEEL
docbot_ai-1.0.1.dist-info/entry_points.txt
docbot_ai-1.0.1.dist-info/top_level.txt
docbot_ai-1.0.1.dist-info/RECORD
