Metadata-Version: 2.1
Name: docbot_ai
Version: 1.0.1
Summary: A LLM tool that generates README files for your files. Uses Groq AI
Home-page: https://github.com/ajogseneca/DocBot
Author: Ajo George
Author-email: ageorge55@myseneca.ca
License: MIT
Classifier: License :: OSI Approved :: MIT License
Classifier: Programming Language :: Python :: 3.12
Classifier: Operating System :: OS Independent
Requires-Python: >=3.10
License-File: LICENSE
Requires-Dist: flake8
Requires-Dist: pytest
Requires-Dist: python-dotenv
Requires-Dist: groq
Provides-Extra: dev
Requires-Dist: flake8; extra == "dev"
Requires-Dist: pytest; extra == "dev"
Requires-Dist: twine>=4.0.2; extra == "dev"
